MANIFEST.in
README.txt
pyproject.toml
setup.cfg
setup.py
strip_duplicates.py
meliae/__init__.py
meliae/_intset.c
meliae/_intset.pyx
meliae/_loader.c
meliae/_loader.pyx
meliae/_scanner.c
meliae/_scanner.pyx
meliae/_scanner_core.c
meliae/_scanner_core.h
meliae/files.py
meliae/loader.py
meliae/perf_counter.py
meliae/scanner.py
meliae/warn.py
meliae.egg-info/PKG-INFO
meliae.egg-info/SOURCES.txt
meliae.egg-info/dependency_links.txt
meliae.egg-info/requires.txt
meliae.egg-info/top_level.txt