Metadata-Version: 2.1
Name: meliae
Version: 0.5.1
Summary: Python Memory Usage Analyzer
Home-page: https://launchpad.net/meliae
Author: John Arbash Meinel
Author-email: john.meinel@canonical.com
License: GNU GPL v3
Download-URL: https://launchpad.net/meliae/+download
Platform: UNKNOWN
Classifier: Development Status :: 4 - Beta
Classifier: Environment :: Console
Classifier: Intended Audience :: Developers
Classifier: License :: OSI Approved :: GNU General Public License (GPL)
Classifier: Operating System :: OS Independent
Classifier: Operating System :: Microsoft :: Windows
Classifier: Operating System :: POSIX
Classifier: Programming Language :: Python
Classifier: Programming Language :: Python :: 2
Classifier: Programming Language :: Python :: 2.7
Classifier: Programming Language :: Python :: 3
Classifier: Programming Language :: Python :: 3.4
Classifier: Programming Language :: Python :: 3.5
Classifier: Programming Language :: Python :: 3.6
Classifier: Programming Language :: Python :: 3.7
Classifier: Programming Language :: Python :: 3.8
Classifier: Programming Language :: Cython
Classifier: Topic :: Software Development :: Debuggers
